MANIFEST.in
README.rst
flickr.py
setup.py
python_flickr.egg-info/PKG-INFO
python_flickr.egg-info/SOURCES.txt
python_flickr.egg-info/dependency_links.txt
python_flickr.egg-info/requires.txt
python_flickr.egg-info/top_level.txt