Metadata-Version: 1.0
Name: python-flickr
Version: 0.2.0
Summary: A Python Library to interface with Flickr REST API, OAuth & JSON Responses
Home-page: https://github.com/michaelhelmick/python-flickr/
Author: Mike Helmick
Author-email: mikehelmick@me.com
License: MIT License
Download-URL: https://github.com/michaelhelmick/python-flickr/zipball/master
Keywords: python flickr oauth api
Platform: UNKNOWN
Classifier: Development Status :: 4 - Beta
Classifier: Intended Audience :: Developers
Classifier: License :: OSI Approved :: MIT License
Classifier: Topic :: Software Development :: Libraries :: Python Modules
Classifier: Topic :: Communications :: Chat
Classifier: Topic :: Internet
